pyserp/__init__.py
pyserp/core/__init__.py
pyserp/core/parser.py
pyserp/core/primitives.py
pyserp/core/searcher.py
pyserp/core/searcher_model.py
pyserp/core/session.py
pyserp/core/utils.py
pyserp/core/exceptions/__init__.py
pyserp/core/exceptions/base.py
pyserp/core/exceptions/parser.py
pyserp/core/exceptions/session.py
pyserp/core/models/__init__.py
pyserp/core/models/general.py
pyserp/core/models/parser.py
pyserp/core/models/session.py
pyserp/providers/__init__.py
pyserp/providers/bing/__init__.py
pyserp/providers/bing/parser.py
pyserp/providers/bing/searcher.py
pyserp/providers/bing/session.py
pyserp/providers/bing/models/__init__.py
pyserp/providers/bing/models/parser.py
pyserp/providers/google/__init__.py
pyserp/providers/google/parser.py
pyserp/providers/google/searcher.py
pyserp/providers/google/session.py
pyserp/providers/google/_internal/exceptions/__init__.py
pyserp/providers/google/_internal/exceptions/parser.py
pyserp/providers/google/models/__init__.py
pyserp/providers/google/models/parser.py
pyserp-1.0.1.dist-info/METADATA
pyserp-1.0.1.dist-info/WHEEL
pyserp-1.0.1.dist-info/licenses/LICENSE
pyserp-1.0.1.dist-info/licenses/NOTICE
pyserp-1.0.1.dist-info/RECORD
