Metadata-Version: 2.4
Name: pyserp
Version: 1.0.1
Summary: A comprehensive asynchronous library for scraping and parsing Search Engine Results Pages (SERPs).
Author-email: Whode <whode@users.noreply.github.com>
License-File: LICENSE
License-File: NOTICE
Classifier: Development Status :: 3 - Alpha
Classifier: Framework :: AsyncIO
Classifier: Intended Audience :: Developers
Classifier: License :: OSI Approved :: Apache Software License
Classifier: Operating System :: OS Independent
Classifier: Programming Language :: Python
Classifier: Programming Language :: Python :: 3
Classifier: Programming Language :: Python :: 3 :: Only
Classifier: Programming Language :: Python :: 3.10
Classifier: Programming Language :: Python :: 3.11
Classifier: Programming Language :: Python :: 3.12
Classifier: Programming Language :: Python :: 3.13
Classifier: Programming Language :: Python :: 3.14
Classifier: Topic :: Internet :: WWW/HTTP
Classifier: Topic :: Software Development :: Libraries :: Python Modules
Classifier: Topic :: Text Processing :: Markup :: HTML
Requires-Python: >=3.10
Requires-Dist: aiohttp~=3.8
Requires-Dist: beautifulsoup4~=4.10
Requires-Dist: lxml~=5.0; python_version < '3.13'
Requires-Dist: lxml~=6.0; python_version >= '3.13'
Requires-Dist: pydantic~=2.0
